{
  "letters": [
    {
      "id": "a",
      "words": [
        "apelsin",
        "avokado",
        "arm"
      ],
      "handGestureImage": "Phonetics/HandGestures/T_HandGesture_a.png",
      "vocalizationSound": "Phonetics/Sounds/Vocalization/Aaaaa.wav",
      "altImage": "Phonetics/AltImages/T_a.png"
    },
    {
      "id": "b",
      "words": [
        "blåbär",
        "barnvagn",
        "byxor"
      ],
      "handGestureImage": "Phonetics/HandGestures/T_HandGesture_b.png",
      "vocalizationSound": "Phonetics/Sounds/Vocalization/Bbbb.wav"
    },
    {
      "id": "d",
      "words": [
        "drake",
        "docka",
        "dator"
      ],
      "handGestureImage": "Phonetics/HandGestures/T_HandGesture_d.png",
      "vocalizationSound": "Phonetics/Sounds/Vocalization/Dddd 2.wav"
    },
    {
      "id": "e",
      "words": [
        "ekorre",
        "eka",
        "eld"
      ],
      "handGestureImage": "Phonetics/HandGestures/T_HandGesture_e.png",
      "vocalizationSound": "Phonetics/Sounds/Vocalization/Eeeee.wav"
    },
    {
      "id": "f",
      "words": [
        "får",
        "fingrar",
        "fjäril"
      ],
      "handGestureImage": "Phonetics/HandGestures/T_HandGesture_f.png",
      "vocalizationSound": "Phonetics/Sounds/Vocalization/Ffffff.wav"
    },
    {
      "id": "g",
      "words": [
        "gris",
        "groda",
        "gaffel"
      ],
      "handGestureImage": "Phonetics/HandGestures/T_HandGesture_g.png",
      "vocalizationSound": "Phonetics/Sounds/Vocalization/Gggg.wav"
    },
    {
      "id": "h",
      "words": [
        "häst",
        "hallon",
        "halsduk"
      ],
      "handGestureImage": "Phonetics/HandGestures/T_HandGesture_h.png",
      "vocalizationSound": "Phonetics/Sounds/Vocalization/Hhhh.wav"
    },
    {
      "id": "i",
      "words": [
        "igelkott",
        "isbitar",
        "insekter"
      ],
      "handGestureImage": "Phonetics/HandGestures/T_HandGesture_i.png",
      "vocalizationSound": "Phonetics/Sounds/Vocalization/Iiiiii.wav"
    },
    {
      "id": "j",
      "words": [
        "julgran",
        "jacka",
        "juice"
      ],
      "handGestureImage": "Phonetics/HandGestures/T_HandGesture_j.png",
      "vocalizationSound": "Phonetics/Sounds/Vocalization/Jjjjj.wav"
    },
    {
      "id": "k",
      "words": [
        "kiwi",
        "kniv",
        "knä"
      ],
      "handGestureImage": "Phonetics/HandGestures/T_HandGesture_k.png",
      "vocalizationSound": "Phonetics/Sounds/Vocalization/Kkkkk.wav"
    },
    {
      "id": "l",
      "words": [
        "lime",
        "lastbil",
        "linjal"
      ],
      "handGestureImage": "Phonetics/HandGestures/T_HandGesture_l.png",
      "vocalizationSound": "Phonetics/Sounds/Vocalization/Llllll.wav"
    },
    {
      "id": "m",
      "words": [
        "marsvin",
        "moln",
        "motorcykel"
      ],
      "handGestureImage": "Phonetics/HandGestures/T_HandGesture_m.png",
      "vocalizationSound": "Phonetics/Sounds/Vocalization/Mmmmm.wav"
    },
    {
      "id": "n",
      "words": [
        "nyckelpiga",
        "nyckel",
        "naglar"
      ],
      "handGestureImage": "Phonetics/HandGestures/T_HandGesture_n.png",
      "vocalizationSound": "Phonetics/Sounds/Vocalization/Nnnnn.wav"
    },
    {
      "id": "o",
      "words": [
        "orange",
        "oliv",
        "ost"
      ],
      "handGestureImage": "Phonetics/HandGestures/T_HandGesture_o.png",
      "vocalizationSound": "Phonetics/Sounds/Vocalization/Oooo.wav"
    },
    {
      "id": "p",
      "words": [
        "persika",
        "potatis",
        "paraply"
      ],
      "handGestureImage": "Phonetics/HandGestures/T_HandGesture_p.png",
      "vocalizationSound": "Phonetics/Sounds/Vocalization/Pppp.wav"
    },
    {
      "id": "r",
      "words": [
        "räv",
        "russin",
        "ryggsäck"
      ],
      "handGestureImage": "Phonetics/HandGestures/T_HandGesture_r.png",
      "vocalizationSound": "Phonetics/Sounds/Vocalization/Rrrr.wav"
    },
    {
      "id": "s",
      "words": [
        "smultron",
        "segelbåt"
      ],
      "handGestureImage": "Phonetics/HandGestures/T_HandGesture_s.png",
      "vocalizationSound": "Phonetics/Sounds/Vocalization/Ssssss.wav"
    },
    {
      "id": "t",
      "words": [
        "tröja",
        "tår",
        "traktor"
      ],
      "handGestureImage": "Phonetics/HandGestures/T_HandGesture_t.png",
      "vocalizationSound": "Phonetics/Sounds/Vocalization/Ttttt.wav"
    },
    {
      "id": "u",
      "words": [
        "ubåt",
        "ugn",
        "undulat"
      ],
      "handGestureImage": "Phonetics/HandGestures/T_HandGesture_u.png",
      "vocalizationSound": "Phonetics/Sounds/Vocalization/Uuuuu.wav"
    },
    {
      "id": "v",
      "words": [
        "vindruva",
        "vas",
        "vattendroppar"
      ],
      "handGestureImage": "Phonetics/HandGestures/T_HandGesture_v.png",
      "vocalizationSound": "Phonetics/Sounds/Vocalization/Vvvvvv.wav"
    },
    {
      "id": "y",
      "words": [
        "yxa",
        "yr"
      ],
      "handGestureImage": "Phonetics/HandGestures/T_HandGesture_y.png",
      "vocalizationSound": "Phonetics/Sounds/Vocalization/Yyyy.wav"
    },
    {
      "id": "å",
      "words": [
        "ål",
        "ånga",
        "åra"
      ],
      "handGestureImage": "Phonetics/HandGestures/T_HandGesture_aa.png",
      "vocalizationSound": "Phonetics/Sounds/Vocalization/Ååååå.wav"
    },
    {
      "id": "ä",
      "words": [
        "ägg",
        "älg",
        "äng"
      ],
      "handGestureImage": "Phonetics/HandGestures/T_HandGesture_aaa.png",
      "vocalizationSound": "Phonetics/Sounds/Vocalization/Ääää.wav"
    },
    {
      "id": "ö",
      "words": [
        "ödla",
        "ögonbryn",
        "öra"
      ],
      "handGestureImage": "Phonetics/HandGestures/T_HandGesture_oo.png",
      "vocalizationSound": "Phonetics/Sounds/Vocalization/Ööööö.wav"
    }
  ]
}