{
  "letters": [
    {
      "id": "a",
      "words": [
        "apelsin",
        "avokado",
        "armar"
      ], "handGestureImage": "Phonetics/HandGestures/T_HandGesture_a.png",
      "altImage": "Phonetics/AltImages/T_a.png"
    },
    {
      "id": "b",
      "words": [
        "blåbär",
        "barnvagn",
        "byxor"
      ], "handGestureImage": "Phonetics/HandGestures/T_HandGesture_b.png"
    },
    {
      "id": "d",
      "words": [
        "drake",
        "docka",
        "dator"
      ], "handGestureImage": "Phonetics/HandGestures/T_HandGesture_d.png"
    },
    {
      "id": "e",
      "words": [
        "ekorre",
        "eka",
        "eld"
      ], "handGestureImage": "Phonetics/HandGestures/T_HandGesture_e.png"
    },
    {
      "id": "f",
      "words": [
        "får",
        "fingrar",
        "fjäril"
      ], "handGestureImage": "Phonetics/HandGestures/T_HandGesture_f.png"
    },
    {
      "id": "g",
      "words": [
        "gris",
        "groda",
        "gaffel"
      ], "handGestureImage": "Phonetics/HandGestures/T_HandGesture_g.png"
    },
    {
      "id": "h",
      "words": [
        "häst",
        "hallon",
        "halsduk"
      ], "handGestureImage": "Phonetics/HandGestures/T_HandGesture_h.png"
    },
    {
      "id": "i",
      "words": [
        "igelkott",
        "isbit",
        "insekter"
      ], "handGestureImage": "Phonetics/HandGestures/T_HandGesture_i.png"
    },
    {
      "id": "j",
      "words": [
        "julgran",
        "jacka",
        "juice"
      ], "handGestureImage": "Phonetics/HandGestures/T_HandGesture_j.png"
    },
    {
      "id": "k",
      "words": [
        "kiwi",
        "kniv",
        "knä"
      ], "handGestureImage": "Phonetics/HandGestures/T_HandGesture_k.png"
    },
    {
      "id": "l",
      "words": [
        "lime",
        "lastbil",
        "linjal"
      ], "handGestureImage": "Phonetics/HandGestures/T_HandGesture_l.png"
    },
    {
      "id": "m",
      "words": [
        "marsvin",
        "moln",
        "motorcykel"
      ], "handGestureImage": "Phonetics/HandGestures/T_HandGesture_m.png"
    },
    {
      "id": "n",
      "words": [
        "nyckelpiga",
        "nyckel",
        "naglar"
      ], "handGestureImage": "Phonetics/HandGestures/T_HandGesture_n.png"
    },
    {
      "id": "o",
      "words": [
        "orange",
        "oliv",
        "ost"
      ], "handGestureImage": "Phonetics/HandGestures/T_HandGesture_o.png"
    },
    {
      "id": "p",
      "words": [
        "persika",
        "potatis",
        "paraply"
      ], "handGestureImage": "Phonetics/HandGestures/T_HandGesture_p.png"
    },
    {
      "id": "r",
      "words": [
        "räv",
        "russin",
        "ryggsäck"
      ], "handGestureImage": "Phonetics/HandGestures/T_HandGesture_r.png"
    },
    {
      "id": "s",
      "words": [
        "smultron",
        "segelbåt"
      ], "handGestureImage": "Phonetics/HandGestures/T_HandGesture_s.png"
    },
    {
      "id": "t",
      "words": [
        "tröja",
        "tår",
        "traktor"
      ], "handGestureImage": "Phonetics/HandGestures/T_HandGesture_t.png"
    },
    {
      "id": "u",
      "words": [
        "ubåt",
        "ugn",
        "undulat"
      ], "handGestureImage": "Phonetics/HandGestures/T_HandGesture_u.png"
    },
    {
      "id": "v",
      "words": [
        "vindruva",
        "vas",
        "vattendroppe"
      ], "handGestureImage": "Phonetics/HandGestures/T_HandGesture_v.png"
    },
    {
      "id": "y",
      "words": [
        "yxa",
        "yr"
      ], "handGestureImage": "Phonetics/HandGestures/T_HandGesture_y.png"
    },
    {
      "id": "å",
      "words": [
        "ål",
        "ånga",
        "åra"
      ], "handGestureImage": "Phonetics/HandGestures/T_HandGesture_aa.png"
    },
    {
      "id": "ä",
      "words": [
        "ägg",
        "älg",
        "äng"
      ], "handGestureImage": "Phonetics/HandGestures/T_HandGesture_aaa.png"
    },
    {
      "id": "ö",
      "words": [
        "ödla",
        "ögonbryn",
        "öra"
      ], "handGestureImage": "Phonetics/HandGestures/T_HandGesture_oo.png"
    }
  ]
}